finbourne_identity/__init__.py
finbourne_identity/api/__init__.py
finbourne_identity/api/application_metadata_api.py
finbourne_identity/api/applications_api.py
finbourne_identity/api/authentication_api.py
finbourne_identity/api/external_token_issuers_api.py
finbourne_identity/api/identity_logs_api.py
finbourne_identity/api/identity_provider_api.py
finbourne_identity/api/me_api.py
finbourne_identity/api/network_zones_api.py
finbourne_identity/api/personal_authentication_tokens_api.py
finbourne_identity/api/roles_api.py
finbourne_identity/api/tokens_api.py
finbourne_identity/api/users_api.py
finbourne_identity/api_client.py
finbourne_identity/api_response.py
finbourne_identity/configuration.py
finbourne_identity/exceptions.py
finbourne_identity/extensions/__init__.py
finbourne_identity/extensions/api_client.py
finbourne_identity/extensions/api_client_factory.py
finbourne_identity/extensions/api_configuration.py
finbourne_identity/extensions/configuration_loaders.py
finbourne_identity/extensions/configuration_options.py
finbourne_identity/extensions/file_access_token.py
finbourne_identity/extensions/proxy_config.py
finbourne_identity/extensions/refreshing_token.py
finbourne_identity/extensions/rest.py
finbourne_identity/extensions/retry.py
finbourne_identity/extensions/socket_keep_alive.py
finbourne_identity/extensions/tcp_keep_alive_connector.py
finbourne_identity/models/__init__.py
finbourne_identity/models/access_controlled_action.py
finbourne_identity/models/access_controlled_resource.py
finbourne_identity/models/action_id.py
finbourne_identity/models/add_scim_response.py
finbourne_identity/models/api_key.py
finbourne_identity/models/authentication_information.py
finbourne_identity/models/claim_mappings.py
finbourne_identity/models/create_api_key.py
finbourne_identity/models/create_application_request.py
finbourne_identity/models/create_external_token_issuer_request.py
finbourne_identity/models/create_network_zone_request.py
finbourne_identity_sdk-2.3.1.dist-info/METADATA
finbourne_identity_sdk-2.3.1.dist-info/WHEEL
finbourne_identity_sdk-2.3.1.dist-info/RECORD
